detecto/__init__.py
detecto/config.py
detecto/core.py
detecto/utils.py
detecto/visualize.py
detecto/tests/__init__.py
detecto/tests/helpers.py
detecto/tests/test_core.py
detecto/tests/test_utils.py
detecto/tests/test_visualize.py
detecto-1.2.2.dist-info/LICENSE
detecto-1.2.2.dist-info/METADATA
detecto-1.2.2.dist-info/WHEEL
detecto-1.2.2.dist-info/top_level.txt
detecto-1.2.2.dist-info/RECORD
