Metadata-Version: 2.1
Name: detecto
Version: 1.2.2
Summary: Build fully-functioning computer vision models with PyTorch
Home-page: https://github.com/alankbi/detecto
Author: Alan Bi
Author-email: alan.bi326@gmail.com
License: UNKNOWN
Platform: UNKNOWN
Classifier: Programming Language :: Python :: 3
Classifier: License :: OSI Approved :: MIT License
Classifier: Operating System :: OS Independent
Requires-Python: >=3.6
License-File: LICENSE
Requires-Dist: matplotlib
Requires-Dist: opencv-python
Requires-Dist: pandas
Requires-Dist: torch
Requires-Dist: torchvision
Requires-Dist: tqdm
